<?xml version="1.0" encoding="UTF-8" standalone="yes"?>
<ns3:dadoTransporteTransportXml xmlns:ns2="http://esus.ufsc.br/dadoinstalacao" xmlns:ns3="http://esus.ufsc.br/dadotransporte" xmlns:ns4="http://esus.ufsc.br/cadastrodomiciliar">
	<uuidDadoSerializado>5444429-eb20ac03-0bce-489b-8eb1-ca4a0ea1e42a</uuidDadoSerializado>
	<tipoDadoSerializado>3</tipoDadoSerializado>
	<codIbge>4205407</codIbge>
	<cnesDadoSerializado>5444429</cnesDadoSerializado>
	<ineDadoSerializado>1382855330</ineDadoSerializado>
	<numLote>1</numLote>
	<ns4:cadastroDomiciliarTransport>
		<condicaoMoradia />
		<enderecoLocalPermanencia>
			<bairro>ITACORUBI</bairro>
			<cep>88034102</cep>
			<codigoIbgeMunicipio>4205407</codigoIbgeMunicipio>
			<complemento>CASA</complemento>
			<nomeLogradouro>AMARO ANTÔNIO VIEIRA</nomeLogradouro>
			<numero>S/N</numero>
			<numeroDneUf>25</numeroDneUf>
			<telefoneContato>99999999999</telefoneContato>
			<telefoneResidencia>99999999999</telefoneResidencia>
			<tipoLogradouroNumeroDne>090</tipoLogradouroNumeroDne>
			<stSemNumero>true</stSemNumero>
			<pontoReferencia>POSTO</pontoReferencia>
			<microArea>FA</microArea>
			<stForaArea>true</stForaArea>
		</enderecoLocalPermanencia>
		<fichaAtualizada>false</fichaAtualizada>
		<statusTermoRecusa>true</statusTermoRecusa>
		<tpCdsOrigem>3</tpCdsOrigem>
		<uuid>5444429-eb20ac03-0bce-489b-8eb1-ca4a0ea1e42a</uuid>
		<uuidFichaOriginadora>5444429-eb20ac03-0bce-489b-8eb1-ca4a0ea1e42a</uuidFichaOriginadora>
		<tipoDeImovel>1</tipoDeImovel>
		<instituicaoPermanencia />
		<headerTransport>
			<profissionalCNS>700609923387762</profissionalCNS>
			<cboCodigo_2002>223505</cboCodigo_2002>
			<cnes>5444429</cnes>
			<ine>1382855330</ine>
			<dataAtendimento>1517234400000</dataAtendimento>
			<codigoIbgeMunicipio>4205407</codigoIbgeMunicipio>
		</headerTransport>
	</ns4:cadastroDomiciliarTransport>
	<ns2:remetente>
		<contraChave>TREINAMENTO</contraChave>
		<uuidInstalacao>TREINAMENTO</uuidInstalacao>
		<cpfOuCnpj>01234567890</cpfOuCnpj>
		<nomeOuRazaoSocial>ADMINISTRADOR INSTALAÇÃO</nomeOuRazaoSocial>
		<fone>8216756527</fone>
		<email>prof@esus.br</email>
		<versaoSistema>3.0.01</versaoSistema>
		<nomeBancoDados>Postgres</nomeBancoDados>
	</ns2:remetente>
	<ns2:originadora>
		<contraChave>TREINAMENTO</contraChave>
		<uuidInstalacao>TREINAMENTO</uuidInstalacao>
		<cpfOuCnpj>01234567890</cpfOuCnpj>
		<nomeOuRazaoSocial>ADMINISTRADOR INSTALAÇÃO</nomeOuRazaoSocial>
		<fone>8216756527</fone>
		<email>prof@esus.br</email>
		<versaoSistema>3.0.01</versaoSistema>
		<nomeBancoDados>Postgres</nomeBancoDados>
	</ns2:originadora>
	<versao major="3" minor="0" revision="0" />
</ns3:dadoTransporteTransportXml>